{
  "instance": "eil51",
  "optimal_value": 426,
  "n": 100,
  "trajectories": [
    {
      "run": 0,
      "cost": 499.0,
      "route": [
        1,
        32,
        11,
        38,
        5,
        49,
        9,
        50,
        16,
        2,
        29,
        21,
        34,
        30,
        10,
        39,
        33,
        45,
        15,
        44,
        37,
        17,
        4,
        18,
        47,
        12,
        46,
        51,
        27,
        48,
        8,
        26,
        31,
        28,
        3,
        20,
        35,
        36,
        22,
        6,
        14,
        25,
        13,
        41,
        19,
        42,
        40,
        43,
        24,
        23,
        7,
        1
      ]
    },
    {
      "run": 1,
      "cost": 583.0,
      "route": [
        1,
        22,
        2,
        16,
        50,
        34,
        30,
        9,
        49,
        10,
        39,
        33,
        45,
        15,
        44,
        37,
        17,
        4,
        47,
        12,
        46,
        51,
        27,
        32,
        11,
        38,
        5,
        6,
        48,
        23,
        7,
        26,
        8,
        31,
        28,
        3,
        20,
        35,
        36,
        29,
        21,
        42,
        19,
        41,
        13,
        25,
        14,
        18,
        24,
        43,
        40,
        1
      ]
    },
    {
      "run": 2,
      "cost": 537.0,
      "route": [
        1,
        22,
        2,
        29,
        21,
        50,
        9,
        49,
        10,
        30,
        34,
        16,
        38,
        11,
        32,
        27,
        51,
        46,
        12,
        47,
        18,
        4,
        17,
        37,
        44,
        15,
        45,
        33,
        39,
        5,
        6,
        48,
        8,
        26,
        31,
        28,
        3,
        20,
        35,
        36,
        23,
        7,
        43,
        24,
        14,
        25,
        13,
        41,
        19,
        42,
        40,
        1
      ]
    },
    {
      "run": 3,
      "cost": 564.0,
      "route": [
        1,
        22,
        28,
        31,
        26,
        8,
        48,
        23,
        7,
        43,
        24,
        14,
        25,
        18,
        4,
        17,
        37,
        15,
        44,
        42,
        19,
        41,
        13,
        40,
        45,
        33,
        10,
        49,
        9,
        50,
        16,
        38,
        11,
        32,
        27,
        51,
        46,
        12,
        47,
        5,
        30,
        34,
        21,
        29,
        2,
        20,
        35,
        36,
        3,
        6,
        39,
        1
      ]
    },
    {
      "run": 4,
      "cost": 503.0,
      "route": [
        1,
        32,
        11,
        38,
        5,
        49,
        9,
        50,
        34,
        30,
        10,
        39,
        33,
        45,
        15,
        44,
        37,
        17,
        4,
        47,
        12,
        46,
        51,
        27,
        48,
        8,
        26,
        31,
        28,
        3,
        20,
        35,
        36,
        29,
        21,
        16,
        2,
        22,
        6,
        14,
        25,
        18,
        13,
        41,
        19,
        42,
        40,
        24,
        23,
        7,
        43,
        1
      ]
    },
    {
      "run": 5,
      "cost": 555.0,
      "route": [
        1,
        27,
        51,
        46,
        12,
        47,
        18,
        4,
        17,
        37,
        15,
        44,
        42,
        19,
        41,
        13,
        25,
        14,
        6,
        48,
        23,
        7,
        43,
        24,
        26,
        8,
        31,
        28,
        3,
        20,
        35,
        36,
        29,
        21,
        34,
        50,
        16,
        9,
        49,
        10,
        30,
        39,
        33,
        45,
        5,
        38,
        11,
        32,
        22,
        2,
        40,
        1
      ]
    },
    {
      "run": 6,
      "cost": 545.0,
      "route": [
        1,
        32,
        11,
        38,
        9,
        50,
        16,
        29,
        21,
        34,
        30,
        10,
        49,
        5,
        12,
        47,
        4,
        17,
        37,
        44,
        15,
        45,
        33,
        39,
        2,
        22,
        28,
        31,
        26,
        8,
        48,
        27,
        51,
        46,
        6,
        14,
        25,
        18,
        13,
        41,
        19,
        42,
        40,
        24,
        23,
        7,
        43,
        3,
        20,
        35,
        36,
        1
      ]
    },
    {
      "run": 7,
      "cost": 532.0,
      "route": [
        1,
        27,
        51,
        46,
        12,
        47,
        18,
        4,
        17,
        37,
        44,
        15,
        45,
        33,
        39,
        10,
        49,
        9,
        50,
        34,
        30,
        16,
        29,
        21,
        2,
        32,
        11,
        38,
        5,
        6,
        48,
        23,
        7,
        26,
        8,
        31,
        28,
        3,
        20,
        35,
        36,
        22,
        43,
        24,
        14,
        25,
        13,
        41,
        19,
        42,
        40,
        1
      ]
    },
    {
      "run": 8,
      "cost": 515.0,
      "route": [
        1,
        27,
        32,
        11,
        38,
        5,
        49,
        9,
        50,
        16,
        2,
        29,
        21,
        34,
        30,
        10,
        39,
        33,
        45,
        15,
        44,
        37,
        17,
        4,
        18,
        47,
        12,
        46,
        51,
        6,
        48,
        8,
        26,
        31,
        28,
        3,
        20,
        35,
        36,
        22,
        7,
        23,
        24,
        14,
        25,
        13,
        41,
        19,
        42,
        40,
        43,
        1
      ]
    },
    {
      "run": 9,
      "cost": 536.0,
      "route": [
        1,
        27,
        51,
        46,
        12,
        47,
        18,
        4,
        17,
        37,
        44,
        15,
        45,
        33,
        10,
        49,
        9,
        50,
        34,
        30,
        39,
        5,
        38,
        11,
        32,
        2,
        29,
        21,
        16,
        22,
        28,
        31,
        8,
        26,
        7,
        23,
        48,
        6,
        14,
        25,
        13,
        41,
        19,
        42,
        40,
        24,
        43,
        3,
        20,
        35,
        36,
        1
      ]
    },
    {
      "run": 10,
      "cost": 545.0,
      "route": [
        1,
        22,
        28,
        31,
        26,
        8,
        48,
        23,
        7,
        43,
        24,
        14,
        25,
        18,
        47,
        12,
        46,
        51,
        27,
        32,
        11,
        38,
        9,
        50,
        34,
        30,
        10,
        49,
        5,
        37,
        17,
        4,
        41,
        19,
        42,
        44,
        15,
        45,
        33,
        39,
        16,
        2,
        29,
        21,
        20,
        35,
        36,
        3,
        6,
        13,
        40,
        1
      ]
    },
    {
      "run": 11,
      "cost": 503.0,
      "route": [
        1,
        32,
        11,
        38,
        5,
        49,
        9,
        50,
        34,
        30,
        10,
        39,
        33,
        45,
        15,
        44,
        37,
        17,
        4,
        47,
        12,
        46,
        51,
        27,
        48,
        8,
        26,
        31,
        28,
        3,
        20,
        35,
        36,
        29,
        21,
        16,
        2,
        22,
        6,
        14,
        25,
        18,
        13,
        41,
        19,
        42,
        40,
        24,
        23,
        7,
        43,
        1
      ]
    },
    {
      "run": 12,
      "cost": 541.0,
      "route": [
        1,
        22,
        28,
        31,
        26,
        8,
        48,
        27,
        51,
        46,
        12,
        47,
        4,
        17,
        37,
        44,
        15,
        45,
        33,
        39,
        10,
        49,
        9,
        50,
        34,
        30,
        38,
        11,
        32,
        2,
        29,
        21,
        16,
        5,
        18,
        14,
        25,
        13,
        41,
        19,
        42,
        40,
        24,
        23,
        7,
        43,
        6,
        3,
        20,
        35,
        36,
        1
      ]
    },
    {
      "run": 13,
      "cost": 563.0,
      "route": [
        1,
        27,
        32,
        11,
        38,
        9,
        50,
        16,
        2,
        29,
        21,
        34,
        30,
        10,
        49,
        5,
        12,
        47,
        4,
        17,
        37,
        15,
        44,
        42,
        19,
        41,
        13,
        25,
        14,
        6,
        48,
        8,
        26,
        31,
        28,
        3,
        20,
        35,
        36,
        22,
        51,
        46,
        18,
        24,
        23,
        7,
        43,
        40,
        45,
        33,
        39,
        1
      ]
    },
    {
      "run": 14,
      "cost": 509.0,
      "route": [
        1,
        32,
        11,
        38,
        5,
        49,
        9,
        50,
        34,
        30,
        10,
        39,
        33,
        45,
        15,
        44,
        37,
        17,
        4,
        18,
        47,
        12,
        46,
        51,
        27,
        48,
        8,
        26,
        31,
        28,
        3,
        20,
        35,
        36,
        2,
        29,
        21,
        16,
        22,
        6,
        14,
        25,
        13,
        41,
        19,
        42,
        40,
        24,
        23,
        7,
        43,
        1
      ]
    },
    {
      "run": 15,
      "cost": 538.0,
      "route": [
        1,
        32,
        11,
        38,
        5,
        49,
        9,
        50,
        34,
        30,
        10,
        39,
        33,
        45,
        15,
        44,
        37,
        17,
        4,
        47,
        12,
        46,
        51,
        27,
        6,
        48,
        23,
        7,
        26,
        8,
        31,
        28,
        3,
        20,
        35,
        36,
        22,
        2,
        29,
        21,
        16,
        24,
        14,
        25,
        18,
        13,
        41,
        19,
        42,
        40,
        43,
        1
      ]
    },
    {
      "run": 16,
      "cost": 517.0,
      "route": [
        1,
        22,
        28,
        31,
        8,
        26,
        7,
        23,
        24,
        14,
        25,
        18,
        47,
        12,
        46,
        51,
        27,
        32,
        11,
        38,
        5,
        49,
        9,
        50,
        34,
        30,
        10,
        39,
        33,
        45,
        15,
        44,
        37,
        17,
        4,
        13,
        41,
        19,
        42,
        40,
        43,
        48,
        6,
        2,
        29,
        21,
        16,
        20,
        35,
        36,
        3,
        1
      ]
    },
    {
      "run": 17,
      "cost": 511.0,
      "route": [
        1,
        32,
        11,
        38,
        5,
        49,
        9,
        50,
        16,
        2,
        29,
        21,
        34,
        30,
        10,
        39,
        33,
        45,
        15,
        44,
        37,
        17,
        4,
        18,
        47,
        12,
        46,
        51,
        27,
        6,
        48,
        8,
        26,
        31,
        28,
        3,
        20,
        35,
        36,
        22,
        7,
        23,
        24,
        14,
        25,
        13,
        41,
        19,
        42,
        40,
        43,
        1
      ]
    },
    {
      "run": 18,
      "cost": 536.0,
      "route": [
        1,
        27,
        51,
        46,
        12,
        47,
        18,
        4,
        17,
        37,
        44,
        15,
        45,
        33,
        10,
        49,
        9,
        50,
        34,
        30,
        39,
        5,
        38,
        11,
        32,
        2,
        29,
        21,
        16,
        20,
        35,
        36,
        3,
        28,
        31,
        8,
        26,
        7,
        23,
        24,
        14,
        25,
        13,
        41,
        19,
        42,
        40,
        6,
        48,
        22,
        43,
        1
      ]
    },
    {
      "run": 19,
      "cost": 524.0,
      "route": [
        1,
        32,
        11,
        38,
        5,
        49,
        9,
        50,
        16,
        2,
        29,
        21,
        34,
        30,
        10,
        39,
        33,
        45,
        15,
        44,
        37,
        17,
        4,
        47,
        12,
        46,
        51,
        27,
        6,
        48,
        23,
        7,
        26,
        8,
        31,
        28,
        3,
        20,
        35,
        36,
        22,
        24,
        14,
        25,
        18,
        13,
        41,
        19,
        42,
        40,
        43,
        1
      ]
    },
    {
      "run": 20,
      "cost": 538.0,
      "route": [
        1,
        27,
        51,
        46,
        12,
        47,
        18,
        4,
        17,
        37,
        44,
        15,
        45,
        33,
        10,
        49,
        9,
        50,
        16,
        29,
        21,
        34,
        30,
        39,
        5,
        38,
        11,
        32,
        2,
        22,
        28,
        31,
        8,
        26,
        7,
        23,
        48,
        6,
        14,
        25,
        13,
        41,
        19,
        42,
        40,
        43,
        24,
        3,
        20,
        35,
        36,
        1
      ]
    },
    {
      "run": 21,
      "cost": 565.0,
      "route": [
        1,
        32,
        11,
        38,
        9,
        50,
        34,
        30,
        10,
        49,
        5,
        12,
        47,
        18,
        4,
        17,
        37,
        15,
        44,
        42,
        19,
        41,
        13,
        25,
        14,
        6,
        27,
        51,
        46,
        48,
        8,
        26,
        31,
        28,
        3,
        20,
        35,
        36,
        2,
        29,
        21,
        16,
        22,
        7,
        23,
        24,
        43,
        40,
        45,
        33,
        39,
        1
      ]
    },
    {
      "run": 22,
      "cost": 503.0,
      "route": [
        1,
        32,
        11,
        38,
        5,
        49,
        9,
        50,
        16,
        2,
        29,
        21,
        34,
        30,
        10,
        39,
        33,
        45,
        15,
        44,
        37,
        17,
        4,
        47,
        12,
        46,
        51,
        27,
        48,
        23,
        7,
        26,
        8,
        31,
        28,
        3,
        20,
        35,
        36,
        22,
        6,
        14,
        25,
        18,
        13,
        41,
        19,
        42,
        40,
        24,
        43,
        1
      ]
    },
    {
      "run": 23,
      "cost": 568.0,
      "route": [
        1,
        27,
        51,
        46,
        12,
        47,
        4,
        17,
        37,
        15,
        44,
        42,
        19,
        41,
        13,
        25,
        14,
        18,
        6,
        48,
        8,
        26,
        31,
        28,
        3,
        20,
        35,
        36,
        29,
        21,
        34,
        50,
        16,
        9,
        49,
        38,
        11,
        32,
        2,
        22,
        7,
        23,
        24,
        43,
        5,
        10,
        30,
        39,
        33,
        45,
        40,
        1
      ]
    },
    {
      "run": 24,
      "cost": 555.0,
      "route": [
        1,
        27,
        51,
        46,
        12,
        47,
        18,
        4,
        17,
        37,
        15,
        44,
        42,
        19,
        41,
        13,
        25,
        14,
        6,
        48,
        23,
        7,
        26,
        8,
        31,
        28,
        3,
        20,
        35,
        36,
        29,
        21,
        50,
        34,
        30,
        9,
        49,
        5,
        38,
        11,
        32,
        2,
        16,
        22,
        43,
        24,
        40,
        45,
        33,
        10,
        39,
        1
      ]
    },
    {
      "run": 25,
      "cost": 555.0,
      "route": [
        1,
        32,
        11,
        38,
        9,
        50,
        34,
        30,
        10,
        49,
        5,
        12,
        47,
        18,
        4,
        17,
        37,
        15,
        44,
        42,
        19,
        41,
        13,
        25,
        14,
        6,
        48,
        23,
        7,
        26,
        8,
        31,
        28,
        3,
        20,
        35,
        36,
        29,
        21,
        16,
        2,
        22,
        27,
        51,
        46,
        24,
        43,
        40,
        45,
        33,
        39,
        1
      ]
    },
    {
      "run": 26,
      "cost": 528.0,
      "route": [
        1,
        32,
        11,
        38,
        5,
        49,
        9,
        50,
        34,
        30,
        10,
        39,
        33,
        45,
        15,
        44,
        37,
        17,
        4,
        18,
        47,
        12,
        46,
        51,
        27,
        48,
        6,
        14,
        25,
        13,
        41,
        19,
        42,
        40,
        24,
        23,
        7,
        26,
        8,
        31,
        28,
        3,
        20,
        35,
        36,
        22,
        2,
        29,
        21,
        16,
        43,
        1
      ]
    },
    {
      "run": 27,
      "cost": 511.0,
      "route": [
        1,
        32,
        11,
        38,
        5,
        49,
        9,
        50,
        34,
        30,
        10,
        39,
        33,
        45,
        15,
        44,
        37,
        17,
        4,
        18,
        47,
        12,
        46,
        51,
        27,
        6,
        48,
        23,
        7,
        26,
        8,
        31,
        28,
        3,
        20,
        35,
        36,
        2,
        29,
        21,
        16,
        22,
        43,
        24,
        14,
        25,
        13,
        41,
        19,
        42,
        40,
        1
      ]
    },
    {
      "run": 28,
      "cost": 579.0,
      "route": [
        1,
        32,
        11,
        38,
        9,
        50,
        16,
        29,
        21,
        34,
        30,
        10,
        49,
        5,
        12,
        47,
        4,
        17,
        37,
        15,
        44,
        42,
        19,
        41,
        13,
        25,
        14,
        6,
        27,
        51,
        46,
        18,
        24,
        23,
        7,
        48,
        8,
        26,
        31,
        28,
        3,
        20,
        35,
        36,
        2,
        22,
        43,
        40,
        45,
        33,
        39,
        1
      ]
    },
    {
      "run": 29,
      "cost": 542.0,
      "route": [
        1,
        22,
        28,
        31,
        26,
        8,
        48,
        6,
        27,
        51,
        46,
        12,
        47,
        4,
        17,
        37,
        44,
        15,
        45,
        33,
        10,
        49,
        9,
        50,
        34,
        30,
        39,
        5,
        38,
        11,
        32,
        2,
        29,
        21,
        16,
        20,
        35,
        36,
        3,
        7,
        23,
        24,
        14,
        25,
        18,
        13,
        41,
        19,
        42,
        40,
        43,
        1
      ]
    },
    {
      "run": 30,
      "cost": 509.0,
      "route": [
        1,
        32,
        11,
        38,
        5,
        49,
        9,
        50,
        34,
        30,
        10,
        39,
        33,
        45,
        15,
        44,
        37,
        17,
        4,
        18,
        47,
        12,
        46,
        51,
        27,
        48,
        8,
        26,
        31,
        28,
        3,
        20,
        35,
        36,
        2,
        29,
        21,
        16,
        22,
        6,
        14,
        25,
        13,
        41,
        19,
        42,
        40,
        24,
        23,
        7,
        43,
        1
      ]
    },
    {
      "run": 31,
      "cost": 517.0,
      "route": [
        1,
        32,
        11,
        38,
        5,
        49,
        9,
        50,
        34,
        30,
        10,
        39,
        33,
        45,
        15,
        44,
        37,
        17,
        4,
        18,
        47,
        12,
        46,
        51,
        27,
        6,
        48,
        23,
        7,
        26,
        8,
        31,
        28,
        3,
        20,
        35,
        36,
        29,
        21,
        16,
        2,
        22,
        14,
        25,
        13,
        41,
        19,
        42,
        40,
        43,
        24,
        1
      ]
    },
    {
      "run": 32,
      "cost": 542.0,
      "route": [
        1,
        32,
        11,
        38,
        9,
        50,
        34,
        30,
        10,
        49,
        5,
        12,
        47,
        4,
        17,
        37,
        15,
        44,
        45,
        33,
        39,
        16,
        2,
        29,
        21,
        20,
        35,
        36,
        3,
        28,
        31,
        8,
        26,
        7,
        23,
        24,
        14,
        25,
        18,
        13,
        41,
        19,
        42,
        40,
        46,
        51,
        27,
        6,
        48,
        22,
        43,
        1
      ]
    },
    {
      "run": 33,
      "cost": 503.0,
      "route": [
        1,
        32,
        11,
        38,
        5,
        49,
        9,
        50,
        16,
        2,
        29,
        21,
        34,
        30,
        10,
        39,
        33,
        45,
        15,
        44,
        37,
        17,
        4,
        47,
        12,
        46,
        51,
        27,
        48,
        23,
        7,
        26,
        8,
        31,
        28,
        3,
        20,
        35,
        36,
        22,
        6,
        14,
        25,
        18,
        13,
        41,
        19,
        42,
        40,
        24,
        43,
        1
      ]
    },
    {
      "run": 34,
      "cost": 520.0,
      "route": [
        1,
        27,
        32,
        11,
        38,
        5,
        49,
        9,
        50,
        34,
        30,
        10,
        39,
        33,
        45,
        15,
        44,
        37,
        17,
        4,
        47,
        12,
        46,
        51,
        6,
        48,
        8,
        26,
        31,
        28,
        3,
        20,
        35,
        36,
        29,
        21,
        16,
        2,
        22,
        7,
        23,
        24,
        14,
        25,
        18,
        13,
        41,
        19,
        42,
        40,
        43,
        1
      ]
    },
    {
      "run": 35,
      "cost": 553.0,
      "route": [
        1,
        22,
        28,
        31,
        8,
        26,
        7,
        23,
        24,
        14,
        25,
        18,
        4,
        47,
        12,
        46,
        51,
        27,
        32,
        11,
        38,
        9,
        50,
        16,
        2,
        29,
        21,
        34,
        30,
        10,
        49,
        5,
        37,
        17,
        44,
        15,
        45,
        33,
        39,
        42,
        19,
        41,
        13,
        40,
        43,
        48,
        6,
        3,
        20,
        35,
        36,
        1
      ]
    },
    {
      "run": 36,
      "cost": 558.0,
      "route": [
        1,
        32,
        11,
        38,
        9,
        50,
        16,
        29,
        21,
        34,
        30,
        10,
        49,
        5,
        12,
        47,
        4,
        17,
        37,
        44,
        15,
        45,
        33,
        39,
        2,
        22,
        28,
        31,
        8,
        26,
        7,
        23,
        24,
        14,
        25,
        18,
        13,
        41,
        19,
        42,
        40,
        6,
        27,
        51,
        46,
        48,
        43,
        3,
        20,
        35,
        36,
        1
      ]
    },
    {
      "run": 37,
      "cost": 505.0,
      "route": [
        1,
        32,
        11,
        38,
        5,
        49,
        9,
        50,
        34,
        30,
        10,
        39,
        33,
        45,
        15,
        44,
        37,
        17,
        4,
        47,
        12,
        51,
        46,
        27,
        48,
        8,
        26,
        31,
        28,
        3,
        20,
        35,
        36,
        29,
        21,
        16,
        2,
        22,
        6,
        14,
        25,
        18,
        13,
        41,
        19,
        42,
        40,
        24,
        23,
        7,
        43,
        1
      ]
    },
    {
      "run": 38,
      "cost": 512.0,
      "route": [
        1,
        32,
        11,
        38,
        5,
        49,
        9,
        50,
        34,
        30,
        10,
        39,
        33,
        45,
        15,
        44,
        37,
        17,
        4,
        18,
        47,
        12,
        46,
        51,
        27,
        6,
        48,
        8,
        26,
        31,
        28,
        3,
        20,
        35,
        36,
        29,
        21,
        16,
        2,
        22,
        7,
        23,
        24,
        14,
        25,
        13,
        41,
        19,
        42,
        40,
        43,
        1
      ]
    },
    {
      "run": 39,
      "cost": 617.0,
      "route": [
        1,
        32,
        11,
        38,
        5,
        49,
        9,
        30,
        34,
        50,
        16,
        29,
        21,
        2,
        22,
        28,
        31,
        8,
        26,
        7,
        23,
        24,
        14,
        25,
        18,
        4,
        47,
        12,
        46,
        51,
        27,
        6,
        48,
        43,
        13,
        41,
        19,
        42,
        44,
        15,
        37,
        17,
        45,
        33,
        10,
        39,
        36,
        35,
        20,
        3,
        40,
        1
      ]
    },
    {
      "run": 40,
      "cost": 511.0,
      "route": [
        1,
        32,
        11,
        38,
        5,
        49,
        9,
        50,
        16,
        2,
        29,
        21,
        34,
        30,
        10,
        39,
        33,
        45,
        15,
        44,
        37,
        17,
        4,
        18,
        47,
        12,
        46,
        51,
        27,
        6,
        48,
        8,
        26,
        31,
        28,
        3,
        20,
        35,
        36,
        22,
        7,
        23,
        24,
        14,
        25,
        13,
        41,
        19,
        42,
        40,
        43,
        1
      ]
    },
    {
      "run": 41,
      "cost": 523.0,
      "route": [
        1,
        32,
        11,
        38,
        5,
        49,
        9,
        50,
        34,
        30,
        10,
        39,
        33,
        45,
        15,
        44,
        37,
        17,
        4,
        18,
        47,
        12,
        51,
        46,
        27,
        6,
        48,
        23,
        7,
        26,
        8,
        31,
        28,
        3,
        20,
        35,
        36,
        29,
        21,
        16,
        2,
        22,
        24,
        14,
        25,
        13,
        41,
        19,
        42,
        40,
        43,
        1
      ]
    },
    {
      "run": 42,
      "cost": 565.0,
      "route": [
        1,
        22,
        28,
        31,
        8,
        26,
        7,
        23,
        24,
        14,
        25,
        18,
        4,
        17,
        37,
        15,
        44,
        45,
        33,
        10,
        49,
        9,
        50,
        34,
        30,
        39,
        21,
        29,
        16,
        2,
        32,
        11,
        38,
        5,
        12,
        47,
        46,
        51,
        27,
        48,
        6,
        43,
        13,
        41,
        19,
        42,
        40,
        3,
        20,
        35,
        36,
        1
      ]
    },
    {
      "run": 43,
      "cost": 512.0,
      "route": [
        1,
        22,
        32,
        11,
        38,
        5,
        49,
        9,
        50,
        34,
        30,
        10,
        39,
        33,
        45,
        15,
        44,
        37,
        17,
        4,
        18,
        47,
        12,
        46,
        51,
        27,
        48,
        8,
        26,
        31,
        28,
        3,
        20,
        35,
        36,
        2,
        29,
        21,
        16,
        6,
        14,
        25,
        13,
        41,
        19,
        42,
        40,
        24,
        23,
        7,
        43,
        1
      ]
    },
    {
      "run": 44,
      "cost": 515.0,
      "route": [
        1,
        32,
        11,
        38,
        5,
        49,
        9,
        50,
        16,
        29,
        21,
        34,
        30,
        10,
        39,
        33,
        45,
        15,
        44,
        37,
        17,
        4,
        47,
        12,
        46,
        51,
        27,
        6,
        48,
        23,
        7,
        26,
        8,
        31,
        28,
        3,
        20,
        35,
        36,
        22,
        2,
        18,
        14,
        25,
        13,
        41,
        19,
        42,
        40,
        24,
        43,
        1
      ]
    },
    {
      "run": 45,
      "cost": 532.0,
      "route": [
        1,
        22,
        2,
        29,
        21,
        50,
        34,
        30,
        9,
        49,
        5,
        38,
        11,
        32,
        27,
        51,
        46,
        12,
        47,
        4,
        17,
        37,
        15,
        44,
        42,
        19,
        41,
        13,
        25,
        14,
        18,
        6,
        48,
        8,
        26,
        31,
        28,
        3,
        20,
        35,
        36,
        16,
        10,
        39,
        33,
        45,
        40,
        24,
        23,
        7,
        43,
        1
      ]
    },
    {
      "run": 46,
      "cost": 563.0,
      "route": [
        1,
        32,
        11,
        38,
        9,
        49,
        10,
        30,
        34,
        50,
        16,
        2,
        29,
        21,
        20,
        35,
        36,
        3,
        28,
        31,
        8,
        26,
        7,
        23,
        24,
        14,
        25,
        18,
        47,
        12,
        46,
        51,
        27,
        6,
        48,
        22,
        5,
        37,
        17,
        4,
        42,
        19,
        41,
        13,
        40,
        44,
        15,
        45,
        33,
        39,
        43,
        1
      ]
    },
    {
      "run": 47,
      "cost": 536.0,
      "route": [
        1,
        27,
        6,
        48,
        23,
        7,
        26,
        8,
        31,
        28,
        3,
        20,
        35,
        36,
        22,
        2,
        29,
        21,
        34,
        50,
        9,
        49,
        38,
        11,
        32,
        51,
        46,
        12,
        47,
        18,
        4,
        17,
        37,
        15,
        44,
        42,
        19,
        41,
        13,
        25,
        14,
        24,
        43,
        40,
        45,
        33,
        10,
        30,
        39,
        5,
        16,
        1
      ]
    },
    {
      "run": 48,
      "cost": 511.0,
      "route": [
        1,
        22,
        28,
        31,
        8,
        26,
        7,
        23,
        24,
        14,
        25,
        18,
        47,
        12,
        46,
        51,
        27,
        32,
        11,
        38,
        5,
        49,
        9,
        50,
        16,
        2,
        29,
        21,
        34,
        30,
        10,
        39,
        33,
        45,
        15,
        44,
        37,
        17,
        4,
        41,
        19,
        42,
        40,
        13,
        6,
        48,
        43,
        3,
        20,
        35,
        36,
        1
      ]
    },
    {
      "run": 49,
      "cost": 578.0,
      "route": [
        1,
        22,
        28,
        31,
        8,
        26,
        7,
        23,
        24,
        14,
        25,
        18,
        4,
        17,
        37,
        44,
        15,
        45,
        33,
        10,
        49,
        9,
        50,
        34,
        30,
        39,
        21,
        29,
        16,
        2,
        11,
        32,
        27,
        6,
        48,
        51,
        46,
        12,
        47,
        5,
        38,
        20,
        35,
        36,
        3,
        43,
        13,
        41,
        19,
        42,
        40,
        1
      ]
    },
    {
      "run": 50,
      "cost": 535.0,
      "route": [
        1,
        32,
        11,
        38,
        5,
        49,
        9,
        50,
        34,
        30,
        10,
        39,
        33,
        45,
        15,
        44,
        37,
        17,
        4,
        47,
        12,
        46,
        51,
        27,
        6,
        48,
        23,
        7,
        26,
        8,
        31,
        28,
        3,
        20,
        35,
        36,
        2,
        29,
        21,
        16,
        22,
        24,
        14,
        25,
        18,
        13,
        41,
        19,
        42,
        40,
        43,
        1
      ]
    },
    {
      "run": 51,
      "cost": 554.0,
      "route": [
        1,
        32,
        11,
        38,
        9,
        50,
        16,
        2,
        29,
        21,
        34,
        30,
        10,
        49,
        5,
        12,
        47,
        18,
        4,
        17,
        37,
        15,
        44,
        42,
        19,
        41,
        13,
        25,
        14,
        6,
        27,
        51,
        46,
        48,
        8,
        26,
        31,
        28,
        3,
        20,
        35,
        36,
        22,
        7,
        23,
        24,
        43,
        40,
        45,
        33,
        39,
        1
      ]
    },
    {
      "run": 52,
      "cost": 545.0,
      "route": [
        1,
        32,
        11,
        38,
        9,
        50,
        16,
        29,
        21,
        34,
        30,
        10,
        49,
        5,
        12,
        47,
        18,
        4,
        17,
        37,
        15,
        44,
        42,
        19,
        41,
        13,
        25,
        14,
        6,
        27,
        51,
        46,
        48,
        23,
        7,
        26,
        8,
        31,
        28,
        3,
        20,
        35,
        36,
        22,
        2,
        39,
        33,
        45,
        40,
        24,
        43,
        1
      ]
    },
    {
      "run": 53,
      "cost": 545.0,
      "route": [
        1,
        32,
        11,
        38,
        9,
        50,
        34,
        30,
        10,
        49,
        5,
        12,
        47,
        18,
        4,
        17,
        37,
        44,
        15,
        45,
        33,
        39,
        21,
        29,
        2,
        16,
        20,
        35,
        36,
        3,
        28,
        31,
        8,
        26,
        7,
        23,
        24,
        14,
        25,
        13,
        41,
        19,
        42,
        40,
        6,
        27,
        51,
        46,
        48,
        22,
        43,
        1
      ]
    },
    {
      "run": 54,
      "cost": 544.0,
      "route": [
        1,
        27,
        32,
        11,
        38,
        9,
        50,
        34,
        30,
        10,
        49,
        5,
        12,
        47,
        4,
        17,
        37,
        44,
        15,
        45,
        33,
        39,
        21,
        29,
        2,
        16,
        20,
        35,
        36,
        3,
        28,
        31,
        8,
        26,
        7,
        23,
        24,
        14,
        25,
        18,
        13,
        41,
        19,
        42,
        40,
        46,
        51,
        6,
        48,
        22,
        43,
        1
      ]
    },
    {
      "run": 55,
      "cost": 551.0,
      "route": [
        1,
        22,
        28,
        31,
        8,
        26,
        7,
        23,
        48,
        6,
        27,
        51,
        46,
        12,
        47,
        4,
        18,
        14,
        25,
        13,
        41,
        19,
        42,
        44,
        15,
        37,
        17,
        5,
        38,
        9,
        50,
        34,
        30,
        10,
        49,
        39,
        33,
        45,
        40,
        24,
        43,
        2,
        16,
        29,
        21,
        20,
        35,
        36,
        3,
        32,
        11,
        1
      ]
    },
    {
      "run": 56,
      "cost": 508.0,
      "route": [
        1,
        27,
        32,
        11,
        38,
        5,
        49,
        9,
        50,
        16,
        29,
        21,
        34,
        30,
        10,
        39,
        33,
        45,
        15,
        44,
        37,
        17,
        4,
        47,
        12,
        46,
        51,
        6,
        48,
        8,
        26,
        31,
        28,
        3,
        20,
        35,
        36,
        22,
        2,
        23,
        7,
        43,
        24,
        14,
        25,
        18,
        13,
        41,
        19,
        42,
        40,
        1
      ]
    },
    {
      "run": 57,
      "cost": 568.0,
      "route": [
        1,
        32,
        11,
        38,
        9,
        49,
        5,
        12,
        47,
        4,
        17,
        37,
        44,
        15,
        45,
        33,
        10,
        30,
        34,
        50,
        16,
        2,
        29,
        21,
        20,
        35,
        36,
        3,
        28,
        31,
        8,
        26,
        7,
        23,
        24,
        14,
        25,
        18,
        13,
        41,
        19,
        42,
        40,
        51,
        46,
        27,
        48,
        6,
        43,
        22,
        39,
        1
      ]
    },
    {
      "run": 58,
      "cost": 502.0,
      "route": [
        1,
        32,
        11,
        38,
        5,
        49,
        9,
        50,
        34,
        30,
        10,
        39,
        33,
        45,
        15,
        44,
        37,
        17,
        4,
        47,
        12,
        46,
        51,
        27,
        6,
        48,
        23,
        7,
        43,
        24,
        14,
        25,
        18,
        13,
        41,
        19,
        42,
        40,
        22,
        28,
        31,
        8,
        26,
        3,
        20,
        35,
        36,
        29,
        21,
        16,
        2,
        1
      ]
    },
    {
      "run": 59,
      "cost": 496.0,
      "route": [
        1,
        22,
        2,
        16,
        50,
        34,
        30,
        9,
        49,
        10,
        39,
        33,
        45,
        15,
        44,
        37,
        17,
        4,
        47,
        12,
        46,
        51,
        27,
        32,
        11,
        38,
        5,
        21,
        29,
        20,
        35,
        36,
        3,
        28,
        31,
        8,
        26,
        7,
        23,
        48,
        6,
        14,
        25,
        18,
        13,
        41,
        19,
        42,
        40,
        24,
        43,
        1
      ]
    },
    {
      "run": 60,
      "cost": 533.0,
      "route": [
        1,
        22,
        28,
        31,
        8,
        26,
        7,
        23,
        48,
        27,
        51,
        46,
        12,
        47,
        4,
        17,
        37,
        44,
        15,
        45,
        33,
        10,
        49,
        9,
        50,
        34,
        30,
        39,
        5,
        38,
        11,
        32,
        2,
        29,
        21,
        16,
        20,
        35,
        36,
        3,
        6,
        14,
        25,
        18,
        13,
        41,
        19,
        42,
        40,
        24,
        43,
        1
      ]
    },
    {
      "run": 61,
      "cost": 535.0,
      "route": [
        1,
        27,
        32,
        11,
        38,
        5,
        49,
        9,
        50,
        34,
        30,
        10,
        39,
        33,
        45,
        15,
        44,
        37,
        17,
        4,
        18,
        47,
        12,
        46,
        51,
        6,
        48,
        23,
        7,
        26,
        8,
        31,
        28,
        3,
        20,
        35,
        36,
        2,
        29,
        21,
        16,
        22,
        24,
        14,
        25,
        13,
        41,
        19,
        42,
        40,
        43,
        1
      ]
    },
    {
      "run": 62,
      "cost": 563.0,
      "route": [
        1,
        32,
        11,
        38,
        9,
        50,
        34,
        30,
        10,
        49,
        5,
        12,
        47,
        4,
        17,
        37,
        15,
        44,
        42,
        19,
        41,
        13,
        25,
        14,
        18,
        6,
        27,
        51,
        46,
        48,
        23,
        7,
        43,
        24,
        26,
        8,
        31,
        28,
        3,
        20,
        35,
        36,
        29,
        21,
        16,
        2,
        22,
        39,
        33,
        45,
        40,
        1
      ]
    },
    {
      "run": 63,
      "cost": 560.0,
      "route": [
        1,
        27,
        51,
        46,
        12,
        47,
        4,
        17,
        37,
        15,
        44,
        45,
        33,
        10,
        49,
        9,
        50,
        16,
        38,
        11,
        32,
        2,
        29,
        21,
        34,
        30,
        39,
        5,
        18,
        14,
        25,
        13,
        41,
        19,
        42,
        40,
        24,
        23,
        7,
        48,
        6,
        8,
        26,
        31,
        28,
        3,
        20,
        35,
        36,
        22,
        43,
        1
      ]
    },
    {
      "run": 64,
      "cost": 564.0,
      "route": [
        1,
        32,
        11,
        38,
        9,
        50,
        34,
        30,
        10,
        49,
        5,
        12,
        47,
        4,
        17,
        37,
        44,
        15,
        45,
        33,
        39,
        16,
        29,
        21,
        2,
        22,
        28,
        31,
        8,
        26,
        7,
        23,
        24,
        14,
        25,
        18,
        13,
        41,
        19,
        42,
        40,
        6,
        48,
        27,
        51,
        46,
        20,
        35,
        36,
        3,
        43,
        1
      ]
    },
    {
      "run": 65,
      "cost": 505.0,
      "route": [
        1,
        32,
        11,
        38,
        5,
        49,
        9,
        50,
        16,
        2,
        29,
        21,
        34,
        30,
        10,
        39,
        33,
        45,
        15,
        44,
        37,
        17,
        4,
        47,
        12,
        51,
        46,
        27,
        48,
        23,
        7,
        26,
        8,
        31,
        28,
        3,
        20,
        35,
        36,
        22,
        6,
        14,
        25,
        18,
        13,
        41,
        19,
        42,
        40,
        24,
        43,
        1
      ]
    },
    {
      "run": 66,
      "cost": 545.0,
      "route": [
        1,
        32,
        11,
        38,
        9,
        50,
        34,
        30,
        10,
        49,
        5,
        12,
        47,
        18,
        4,
        17,
        37,
        44,
        15,
        45,
        33,
        39,
        21,
        29,
        2,
        16,
        22,
        28,
        31,
        8,
        26,
        7,
        23,
        24,
        14,
        25,
        13,
        41,
        19,
        42,
        40,
        46,
        51,
        27,
        6,
        48,
        43,
        3,
        20,
        35,
        36,
        1
      ]
    },
    {
      "run": 67,
      "cost": 526.0,
      "route": [
        1,
        22,
        28,
        31,
        8,
        26,
        7,
        23,
        24,
        14,
        25,
        18,
        4,
        17,
        37,
        15,
        44,
        42,
        19,
        41,
        13,
        40,
        45,
        33,
        10,
        49,
        9,
        50,
        16,
        29,
        21,
        34,
        30,
        39,
        5,
        38,
        11,
        32,
        27,
        51,
        46,
        12,
        47,
        6,
        48,
        43,
        2,
        20,
        35,
        36,
        3,
        1
      ]
    },
    {
      "run": 68,
      "cost": 491.0,
      "route": [
        1,
        27,
        32,
        11,
        38,
        5,
        49,
        9,
        50,
        34,
        30,
        10,
        39,
        33,
        45,
        15,
        44,
        37,
        17,
        4,
        47,
        12,
        46,
        51,
        6,
        48,
        23,
        7,
        43,
        24,
        14,
        25,
        18,
        13,
        41,
        19,
        42,
        40,
        2,
        16,
        29,
        21,
        20,
        35,
        36,
        3,
        28,
        31,
        8,
        26,
        22,
        1
      ]
    },
    {
      "run": 69,
      "cost": 534.0,
      "route": [
        1,
        27,
        51,
        46,
        12,
        47,
        4,
        18,
        25,
        14,
        6,
        48,
        8,
        26,
        31,
        28,
        3,
        20,
        35,
        36,
        22,
        2,
        29,
        21,
        50,
        9,
        49,
        10,
        30,
        34,
        16,
        11,
        32,
        38,
        5,
        37,
        17,
        44,
        15,
        45,
        33,
        39,
        42,
        19,
        41,
        13,
        40,
        24,
        23,
        7,
        43,
        1
      ]
    },
    {
      "run": 70,
      "cost": 514.0,
      "route": [
        1,
        22,
        2,
        16,
        50,
        9,
        49,
        38,
        11,
        32,
        27,
        51,
        46,
        12,
        47,
        4,
        18,
        25,
        14,
        6,
        48,
        8,
        26,
        31,
        28,
        3,
        20,
        35,
        36,
        29,
        21,
        34,
        30,
        10,
        39,
        33,
        45,
        15,
        44,
        37,
        17,
        42,
        19,
        41,
        13,
        40,
        5,
        23,
        7,
        43,
        24,
        1
      ]
    },
    {
      "run": 71,
      "cost": 590.0,
      "route": [
        1,
        22,
        28,
        31,
        26,
        8,
        48,
        6,
        27,
        51,
        46,
        12,
        47,
        4,
        17,
        37,
        15,
        44,
        42,
        19,
        41,
        13,
        25,
        14,
        18,
        24,
        23,
        7,
        43,
        32,
        11,
        38,
        9,
        49,
        10,
        30,
        34,
        50,
        16,
        29,
        21,
        2,
        20,
        35,
        36,
        3,
        39,
        33,
        45,
        5,
        40,
        1
      ]
    },
    {
      "run": 72,
      "cost": 502.0,
      "route": [
        1,
        32,
        11,
        38,
        5,
        49,
        9,
        50,
        16,
        2,
        29,
        21,
        34,
        30,
        10,
        39,
        33,
        45,
        15,
        44,
        37,
        17,
        4,
        47,
        12,
        46,
        51,
        27,
        48,
        8,
        26,
        31,
        28,
        3,
        20,
        35,
        36,
        22,
        6,
        14,
        25,
        18,
        13,
        41,
        19,
        42,
        40,
        24,
        23,
        7,
        43,
        1
      ]
    },
    {
      "run": 73,
      "cost": 533.0,
      "route": [
        1,
        22,
        28,
        31,
        8,
        26,
        7,
        23,
        24,
        14,
        25,
        18,
        4,
        17,
        37,
        15,
        44,
        42,
        19,
        41,
        13,
        40,
        45,
        33,
        10,
        49,
        9,
        50,
        34,
        30,
        39,
        5,
        38,
        11,
        32,
        27,
        46,
        51,
        12,
        47,
        6,
        48,
        43,
        2,
        16,
        29,
        21,
        20,
        35,
        36,
        3,
        1
      ]
    },
    {
      "run": 74,
      "cost": 522.0,
      "route": [
        1,
        22,
        28,
        31,
        8,
        26,
        7,
        23,
        24,
        14,
        25,
        18,
        47,
        12,
        46,
        51,
        27,
        32,
        11,
        38,
        5,
        49,
        9,
        50,
        34,
        30,
        10,
        39,
        33,
        45,
        15,
        44,
        37,
        17,
        4,
        41,
        19,
        42,
        40,
        13,
        6,
        48,
        43,
        3,
        20,
        35,
        36,
        2,
        16,
        29,
        21,
        1
      ]
    },
    {
      "run": 75,
      "cost": 520.0,
      "route": [
        1,
        22,
        28,
        31,
        8,
        26,
        7,
        23,
        24,
        14,
        25,
        18,
        47,
        12,
        46,
        51,
        27,
        32,
        11,
        38,
        5,
        49,
        9,
        50,
        16,
        2,
        29,
        21,
        34,
        30,
        10,
        39,
        33,
        45,
        15,
        44,
        37,
        17,
        4,
        13,
        41,
        19,
        42,
        40,
        6,
        48,
        43,
        3,
        20,
        35,
        36,
        1
      ]
    },
    {
      "run": 76,
      "cost": 554.0,
      "route": [
        1,
        32,
        11,
        38,
        9,
        50,
        16,
        2,
        29,
        21,
        34,
        30,
        10,
        49,
        5,
        12,
        47,
        4,
        17,
        37,
        44,
        15,
        45,
        33,
        39,
        46,
        51,
        27,
        6,
        48,
        23,
        7,
        26,
        8,
        31,
        28,
        3,
        20,
        35,
        36,
        22,
        24,
        14,
        25,
        18,
        13,
        41,
        19,
        42,
        40,
        43,
        1
      ]
    },
    {
      "run": 77,
      "cost": 510.0,
      "route": [
        1,
        22,
        28,
        31,
        8,
        26,
        7,
        23,
        48,
        27,
        32,
        11,
        38,
        5,
        49,
        9,
        50,
        34,
        30,
        10,
        39,
        33,
        45,
        15,
        44,
        37,
        17,
        4,
        18,
        47,
        12,
        46,
        51,
        6,
        14,
        25,
        13,
        41,
        19,
        42,
        40,
        24,
        43,
        2,
        29,
        21,
        16,
        20,
        35,
        36,
        3,
        1
      ]
    },
    {
      "run": 78,
      "cost": 528.0,
      "route": [
        1,
        22,
        28,
        31,
        26,
        8,
        48,
        27,
        32,
        11,
        38,
        9,
        50,
        34,
        30,
        10,
        49,
        5,
        12,
        47,
        18,
        4,
        17,
        37,
        44,
        15,
        45,
        33,
        39,
        21,
        29,
        16,
        2,
        20,
        35,
        36,
        3,
        51,
        46,
        6,
        14,
        25,
        13,
        41,
        19,
        42,
        40,
        24,
        23,
        7,
        43,
        1
      ]
    },
    {
      "run": 79,
      "cost": 525.0,
      "route": [
        1,
        32,
        11,
        38,
        5,
        49,
        9,
        50,
        34,
        30,
        10,
        39,
        33,
        45,
        15,
        44,
        37,
        17,
        4,
        47,
        12,
        46,
        51,
        27,
        6,
        48,
        23,
        7,
        26,
        8,
        31,
        28,
        3,
        20,
        35,
        36,
        22,
        2,
        16,
        29,
        21,
        18,
        14,
        25,
        13,
        41,
        19,
        42,
        40,
        24,
        43,
        1
      ]
    },
    {
      "run": 80,
      "cost": 517.0,
      "route": [
        1,
        27,
        51,
        46,
        12,
        47,
        4,
        18,
        25,
        14,
        6,
        48,
        8,
        26,
        31,
        28,
        3,
        20,
        35,
        36,
        29,
        21,
        50,
        34,
        30,
        9,
        49,
        10,
        39,
        33,
        45,
        15,
        44,
        37,
        17,
        42,
        19,
        41,
        13,
        40,
        5,
        38,
        11,
        32,
        2,
        16,
        22,
        7,
        23,
        24,
        43,
        1
      ]
    },
    {
      "run": 81,
      "cost": 594.0,
      "route": [
        1,
        32,
        11,
        38,
        9,
        49,
        5,
        12,
        47,
        18,
        4,
        17,
        37,
        15,
        44,
        45,
        33,
        10,
        30,
        34,
        50,
        16,
        2,
        29,
        21,
        20,
        35,
        36,
        3,
        28,
        31,
        8,
        26,
        7,
        23,
        24,
        14,
        25,
        13,
        41,
        19,
        42,
        40,
        6,
        48,
        27,
        51,
        46,
        22,
        43,
        39,
        1
      ]
    },
    {
      "run": 82,
      "cost": 578.0,
      "route": [
        1,
        27,
        51,
        46,
        12,
        47,
        18,
        4,
        17,
        37,
        15,
        44,
        42,
        19,
        41,
        13,
        25,
        14,
        6,
        48,
        23,
        7,
        26,
        8,
        31,
        28,
        3,
        20,
        35,
        36,
        2,
        29,
        21,
        50,
        34,
        30,
        9,
        49,
        10,
        39,
        33,
        45,
        5,
        38,
        11,
        32,
        22,
        16,
        24,
        43,
        40,
        1
      ]
    },
    {
      "run": 83,
      "cost": 568.0,
      "route": [
        1,
        32,
        11,
        38,
        9,
        50,
        16,
        2,
        29,
        21,
        34,
        30,
        10,
        49,
        5,
        12,
        47,
        18,
        4,
        17,
        37,
        44,
        15,
        45,
        33,
        39,
        42,
        19,
        41,
        13,
        25,
        14,
        6,
        27,
        51,
        46,
        48,
        8,
        26,
        31,
        28,
        3,
        20,
        35,
        36,
        22,
        7,
        23,
        24,
        43,
        40,
        1
      ]
    },
    {
      "run": 84,
      "cost": 523.0,
      "route": [
        1,
        27,
        51,
        46,
        12,
        47,
        4,
        17,
        37,
        44,
        15,
        45,
        33,
        39,
        10,
        49,
        9,
        50,
        16,
        2,
        29,
        21,
        34,
        30,
        5,
        38,
        11,
        32,
        22,
        28,
        31,
        8,
        26,
        7,
        23,
        48,
        6,
        14,
        25,
        18,
        13,
        41,
        19,
        42,
        40,
        24,
        43,
        36,
        35,
        20,
        3,
        1
      ]
    },
    {
      "run": 85,
      "cost": 615.0,
      "route": [
        1,
        22,
        28,
        31,
        8,
        26,
        7,
        23,
        48,
        6,
        27,
        51,
        46,
        12,
        47,
        18,
        4,
        17,
        37,
        15,
        44,
        45,
        33,
        10,
        49,
        9,
        50,
        34,
        30,
        39,
        21,
        29,
        2,
        16,
        38,
        11,
        32,
        5,
        42,
        19,
        41,
        13,
        25,
        14,
        24,
        43,
        3,
        20,
        35,
        36,
        40,
        1
      ]
    },
    {
      "run": 86,
      "cost": 565.0,
      "route": [
        1,
        22,
        28,
        31,
        8,
        26,
        7,
        23,
        24,
        14,
        25,
        18,
        47,
        12,
        46,
        51,
        27,
        32,
        11,
        38,
        9,
        50,
        34,
        30,
        10,
        49,
        5,
        37,
        17,
        4,
        13,
        41,
        19,
        42,
        44,
        15,
        45,
        33,
        39,
        21,
        29,
        16,
        2,
        20,
        35,
        36,
        3,
        48,
        6,
        43,
        40,
        1
      ]
    },
    {
      "run": 87,
      "cost": 564.0,
      "route": [
        1,
        22,
        28,
        31,
        8,
        26,
        7,
        23,
        48,
        27,
        51,
        46,
        12,
        47,
        4,
        17,
        37,
        15,
        44,
        45,
        33,
        10,
        49,
        9,
        50,
        34,
        30,
        39,
        38,
        11,
        32,
        2,
        16,
        29,
        21,
        20,
        35,
        36,
        3,
        6,
        14,
        25,
        18,
        13,
        41,
        19,
        42,
        40,
        24,
        43,
        5,
        1
      ]
    },
    {
      "run": 88,
      "cost": 509.0,
      "route": [
        1,
        32,
        11,
        38,
        5,
        49,
        9,
        50,
        34,
        30,
        10,
        39,
        33,
        45,
        15,
        44,
        37,
        17,
        4,
        18,
        47,
        12,
        46,
        51,
        27,
        48,
        8,
        26,
        31,
        28,
        3,
        20,
        35,
        36,
        2,
        29,
        21,
        16,
        22,
        6,
        14,
        25,
        13,
        41,
        19,
        42,
        40,
        24,
        23,
        7,
        43,
        1
      ]
    },
    {
      "run": 89,
      "cost": 542.0,
      "route": [
        1,
        32,
        11,
        38,
        9,
        50,
        34,
        30,
        10,
        49,
        5,
        12,
        47,
        18,
        4,
        17,
        37,
        44,
        15,
        45,
        33,
        39,
        21,
        29,
        2,
        16,
        20,
        35,
        36,
        3,
        28,
        31,
        8,
        26,
        7,
        23,
        24,
        14,
        25,
        13,
        41,
        19,
        42,
        40,
        6,
        48,
        27,
        46,
        51,
        22,
        43,
        1
      ]
    },
    {
      "run": 90,
      "cost": 499.0,
      "route": [
        1,
        32,
        11,
        38,
        5,
        49,
        9,
        50,
        34,
        30,
        10,
        39,
        33,
        45,
        15,
        44,
        37,
        17,
        4,
        18,
        47,
        12,
        46,
        51,
        27,
        48,
        8,
        26,
        31,
        28,
        3,
        20,
        35,
        36,
        29,
        21,
        16,
        2,
        22,
        6,
        14,
        25,
        13,
        41,
        19,
        42,
        40,
        24,
        23,
        7,
        43,
        1
      ]
    },
    {
      "run": 91,
      "cost": 532.0,
      "route": [
        1,
        22,
        28,
        31,
        8,
        26,
        7,
        23,
        48,
        27,
        51,
        46,
        12,
        47,
        18,
        4,
        17,
        37,
        15,
        44,
        45,
        33,
        10,
        49,
        9,
        50,
        34,
        30,
        39,
        5,
        38,
        11,
        32,
        2,
        29,
        21,
        16,
        20,
        35,
        36,
        3,
        6,
        14,
        25,
        13,
        41,
        19,
        42,
        40,
        24,
        43,
        1
      ]
    },
    {
      "run": 92,
      "cost": 617.0,
      "route": [
        1,
        22,
        28,
        31,
        8,
        26,
        7,
        23,
        48,
        27,
        32,
        11,
        38,
        9,
        50,
        16,
        2,
        29,
        21,
        34,
        30,
        10,
        49,
        5,
        12,
        47,
        4,
        17,
        37,
        44,
        15,
        45,
        33,
        39,
        42,
        19,
        41,
        13,
        25,
        14,
        6,
        51,
        46,
        18,
        24,
        43,
        20,
        35,
        36,
        3,
        40,
        1
      ]
    },
    {
      "run": 93,
      "cost": 558.0,
      "route": [
        1,
        27,
        51,
        46,
        12,
        47,
        18,
        4,
        17,
        37,
        44,
        15,
        45,
        33,
        10,
        49,
        9,
        50,
        34,
        30,
        39,
        21,
        29,
        16,
        2,
        32,
        11,
        38,
        5,
        6,
        48,
        23,
        7,
        26,
        8,
        31,
        28,
        3,
        20,
        35,
        36,
        22,
        24,
        14,
        25,
        13,
        41,
        19,
        42,
        40,
        43,
        1
      ]
    },
    {
      "run": 94,
      "cost": 531.0,
      "route": [
        1,
        32,
        11,
        38,
        9,
        50,
        16,
        29,
        21,
        34,
        30,
        49,
        10,
        39,
        33,
        45,
        15,
        44,
        37,
        17,
        4,
        18,
        47,
        12,
        46,
        51,
        27,
        48,
        23,
        7,
        26,
        8,
        31,
        28,
        3,
        20,
        35,
        36,
        2,
        22,
        6,
        14,
        25,
        13,
        41,
        19,
        42,
        40,
        5,
        24,
        43,
        1
      ]
    },
    {
      "run": 95,
      "cost": 515.0,
      "route": [
        1,
        22,
        28,
        31,
        8,
        26,
        7,
        23,
        24,
        14,
        25,
        18,
        47,
        12,
        46,
        51,
        27,
        32,
        11,
        38,
        5,
        49,
        9,
        50,
        34,
        30,
        10,
        39,
        33,
        45,
        15,
        44,
        37,
        17,
        4,
        41,
        19,
        42,
        40,
        13,
        6,
        48,
        43,
        3,
        20,
        35,
        36,
        2,
        29,
        21,
        16,
        1
      ]
    },
    {
      "run": 96,
      "cost": 521.0,
      "route": [
        1,
        22,
        28,
        31,
        8,
        26,
        7,
        23,
        24,
        14,
        25,
        18,
        47,
        12,
        46,
        51,
        27,
        32,
        11,
        38,
        5,
        49,
        9,
        50,
        34,
        30,
        10,
        39,
        33,
        45,
        15,
        44,
        37,
        17,
        4,
        13,
        41,
        19,
        42,
        40,
        6,
        48,
        43,
        2,
        29,
        21,
        16,
        20,
        35,
        36,
        3,
        1
      ]
    },
    {
      "run": 97,
      "cost": 547.0,
      "route": [
        1,
        27,
        46,
        51,
        47,
        12,
        5,
        38,
        9,
        50,
        34,
        30,
        10,
        49,
        11,
        32,
        2,
        29,
        21,
        16,
        20,
        35,
        36,
        3,
        28,
        31,
        8,
        26,
        7,
        23,
        24,
        14,
        25,
        18,
        4,
        17,
        37,
        15,
        44,
        42,
        19,
        41,
        13,
        40,
        45,
        33,
        39,
        22,
        48,
        6,
        43,
        1
      ]
    },
    {
      "run": 98,
      "cost": 531.0,
      "route": [
        1,
        32,
        11,
        38,
        5,
        49,
        9,
        50,
        34,
        30,
        10,
        39,
        33,
        45,
        15,
        44,
        37,
        17,
        4,
        18,
        47,
        12,
        46,
        51,
        27,
        6,
        48,
        23,
        7,
        26,
        8,
        31,
        28,
        3,
        20,
        35,
        36,
        2,
        29,
        21,
        16,
        22,
        24,
        14,
        25,
        13,
        41,
        19,
        42,
        40,
        43,
        1
      ]
    },
    {
      "run": 99,
      "cost": 509.0,
      "route": [
        1,
        22,
        28,
        31,
        26,
        8,
        48,
        27,
        32,
        11,
        38,
        5,
        49,
        9,
        50,
        34,
        30,
        10,
        39,
        33,
        45,
        15,
        44,
        37,
        17,
        4,
        18,
        47,
        12,
        46,
        51,
        6,
        14,
        25,
        13,
        41,
        19,
        42,
        40,
        24,
        23,
        7,
        43,
        2,
        29,
        21,
        16,
        20,
        35,
        36,
        3,
        1
      ]
    }
  ]
}